README.txt
setup.py
src/zif/__init__.py
src/zif.gzipper.egg-info/PKG-INFO
src/zif.gzipper.egg-info/SOURCES.txt
src/zif.gzipper.egg-info/dependency_links.txt
src/zif.gzipper.egg-info/namespace_packages.txt
src/zif.gzipper.egg-info/not-zip-safe
src/zif.gzipper.egg-info/requires.txt
src/zif.gzipper.egg-info/top_level.txt
src/zif/gzipper/LICENSE.txt
src/zif/gzipper/README.txt
src/zif/gzipper/__init__.py
src/zif/gzipper/gzipper.py
src/zif/gzipper/queues.py
