Metadata-Version: 1.0
Name: zif.gzipper
Version: 0.2
Summary: WSGI middleware providing gzip compression for HTTP server output.
Home-page: http://zif.svn.sourceforge.net/viewvc/zif/zif.gzipper
Author: Jim Washington
Author-email: jwashin@users.sourceforge.net
License: BSD
Keywords: gzipper gzip wsgi middleware zope3
Platform: UNKNOWN
